abbreviator/__init__.py
abbreviator/abbreviate.py
abbreviator/core.py
abbreviator-0.0.4.dist-info/LICENSE
abbreviator-0.0.4.dist-info/METADATA
abbreviator-0.0.4.dist-info/WHEEL
abbreviator-0.0.4.dist-info/top_level.txt
abbreviator-0.0.4.dist-info/RECORD
