Metadata-Version: 2.1
Name: abbreviator
Version: 0.0.4
Summary: Abbreviate Long Sentences/Names based on hyphenation
Home-page: https://github.com/BOLD-lab/abbreviator
Author: Stephanie Wagenaar
Author-email: stephanie.wagenaar@boldcm.eu
License: UNKNOWN
Platform: UNKNOWN
Classifier: Programming Language :: Python :: 3
Classifier: License :: OSI Approved :: MIT License
Classifier: Operating System :: OS Independent
Requires-Python: >=3.6
License-File: LICENSE
Requires-Dist: pyphen (>=0.11.0)
